iterai/__init__.py
iterai/cli.py
iterai/config.py
iterai/dag.py
iterai/diff.py
iterai/llm.py
iterai/node.py
iterai/storage.py
iterai/types.py
iterai-0.2.0.dist-info/METADATA
iterai-0.2.0.dist-info/WHEEL
iterai-0.2.0.dist-info/entry_points.txt
iterai-0.2.0.dist-info/licenses/LICENSE
iterai-0.2.0.dist-info/RECORD
