Metadata-Version: 2.4
Name: iterai
Version: 0.2.0
Summary: A local-first, graph-based LLM refinement engine with transparent planning, diff-based evolution, and multi-model synthesis.
License: MIT
License-File: LICENSE
Author: ra0x3
Author-email: spam.rashad@protonmail.com
Requires-Python: >=3.10,<3.13
Classifier: License :: OSI Approved :: MIT License
Classifier: Programming Language :: Python :: 3
Classifier: Programming Language :: Python :: 3.10
Classifier: Programming Language :: Python :: 3.11
Classifier: Programming Language :: Python :: 3.12
Requires-Dist: aiofiles (>=23.2.1,<24.0.0)
Requires-Dist: litellm (>=1.34.4,<2.0.0)
Requires-Dist: rich (>=13.9.3,<14.0.0)
Requires-Dist: toml (>=0.10.2,<0.11.0)
